{
  "url": "https://api.github.com/repos/tablacus/TablacusExplorer/releases/223856702",

  "assets_url": "https://api.github.com/repos/tablacus/TablacusExplorer/releases/223856702/assets",

  "upload_url": "https://uploads.github.com/repos/tablacus/TablacusExplorer/releases/223856702/assets{?name,label}",

  "html_url": "https://github.com/tablacus/TablacusExplorer/releases/tag/25.6.8",

  "id": 223856702,
  "author": {
    "login": "tablacus",

    "id": 5156977,
    "node_id": "MDQ6VXNlcjUxNTY5Nzc=",

    "avatar_url": "https://avatars.githubusercontent.com/u/5156977?v=4",

    "gravatar_id": "",

    "url": "https://api.github.com/users/tablacus",

    "html_url": "https://github.com/tablacus",

    "followers_url": "https://api.github.com/users/tablacus/followers",

    "following_url": "https://api.github.com/users/tablacus/following{/other_user}",

    "gists_url": "https://api.github.com/users/tablacus/gists{/gist_id}",

    "starred_url": "https://api.github.com/users/tablacus/starred{/owner}{/repo}",

    "subscriptions_url": "https://api.github.com/users/tablacus/subscriptions",

    "organizations_url": "https://api.github.com/users/tablacus/orgs",

    "repos_url": "https://api.github.com/users/tablacus/repos",

    "events_url": "https://api.github.com/users/tablacus/events{/privacy}",

    "received_events_url": "https://api.github.com/users/tablacus/received_events",

    "type": "User",

    "user_view_type": "public",

    "site_admin": false
  },
  "node_id": "RE_kwDOALVDDs4NV8g-",

  "tag_name": "25.6.8",

  "target_commitish": "master",

  "name": "",

  "draft": false,
  "prerelease": false,
  "created_at": "2025-06-08T12:57:14Z",

  "published_at": "2025-06-08T13:12:25Z",

  "assets": [
    {
      "url": "https://api.github.com/repos/tablacus/TablacusExplorer/releases/assets/262041649",

      "id": 262041649,
      "node_id": "RA_kwDOALVDDs4PnnAx",

      "name": "te250608.zip",

      "label": null,
      "uploader": {
        "login": "tablacus",

        "id": 5156977,
        "node_id": "MDQ6VXNlcjUxNTY5Nzc=",

        "avatar_url": "https://avatars.githubusercontent.com/u/5156977?v=4",

        "gravatar_id": "",

        "url": "https://api.github.com/users/tablacus",

        "html_url": "https://github.com/tablacus",

        "followers_url": "https://api.github.com/users/tablacus/followers",

        "following_url": "https://api.github.com/users/tablacus/following{/other_user}",

        "gists_url": "https://api.github.com/users/tablacus/gists{/gist_id}",

        "starred_url": "https://api.github.com/users/tablacus/starred{/owner}{/repo}",

        "subscriptions_url": "https://api.github.com/users/tablacus/subscriptions",

        "organizations_url": "https://api.github.com/users/tablacus/orgs",

        "repos_url": "https://api.github.com/users/tablacus/repos",

        "events_url": "https://api.github.com/users/tablacus/events{/privacy}",

        "received_events_url": "https://api.github.com/users/tablacus/received_events",

        "type": "User",

        "user_view_type": "public",

        "site_admin": false
      },
      "content_type": "application/x-zip-compressed",

      "state": "uploaded",

      "size": 959787,
      "digest": "sha256:f02cbbff1d7ff3c377c20fa46f2f9fe60a292d73eaa7f9fe0e9647d2ab89d2d2",

      
      "created_at": "2025-06-08T13:12:18Z",

      "updated_at": "2025-06-08T13:12:20Z",

      "browser_download_url": "https://github.com/tablacus/TablacusExplorer/releases/download/25.6.8/te250608.zip"
    }
  ],
  "tarball_url": "https://api.github.com/repos/tablacus/TablacusExplorer/tarball/25.6.8",

  "zipball_url": "https://api.github.com/repos/tablacus/TablacusExplorer/zipball/25.6.8",

  "body": "__Thank you for everything, Trident__\r\n- スクリプトエラーの表示周りの調整\r\n_表示やドラッグ＆ドロップがおかしい場合_\r\nhttps://wooty.hatenadiary.org/entry/2025/02/03/233544\r\n_これでもダメな場合のとりあえずの回避策_\r\nTablacus Eplorerを閉じてから フォルダ`lib`にある`tewv32.dll`と`tewv64.dll`を削除してみて下さい。\r\n- If the Blink version doesn't work\r\n_Delete WebView2's dll_\r\nAs a temporary workaround, close Tablacus Explorer again, delete tewv32.dll and tewv64.dll from the lib folder, and then try launching the application once more.\r\n\r\n[VirusTotal](https://www.virustotal.com/gui/file/f02cbbff1d7ff3c377c20fa46f2f9fe60a292d73eaa7f9fe0e9647d2ab89d2d2)\r\n"
}

