{"url":"https://api.github.com/repos/tablacus/TablacusExplorer/releases/33722383",
"assets_url":"https://api.github.com/repos/tablacus/TablacusExplorer/releases/33722383/assets",
"upload_url":"https://uploads.github.com/repos/tablacus/TablacusExplorer/releases/33722383/assets{?name,label}",
"html_url":"https://github.com/tablacus/TablacusExplorer/releases/tag/20.11.10",
"id":33722383,
"node_id":"MDc6UmVsZWFzZTMzNzIyMzgz",
"tag_name":"20.11.10",
"target_commitish":"master",
"name":"",
"draft":false,"author":{"login":"tablacus",
"id":5156977,
"node_id":"MDQ6VXNlcjUxNTY5Nzc=",
"avatar_url":"https://avatars0.githubusercontent.com/u/5156977?v=4",
"gravatar_id":"",
"url":"https://api.github.com/users/tablacus",
"html_url":"https://github.com/tablacus",
"followers_url":"https://api.github.com/users/tablacus/followers",
"following_url":"https://api.github.com/users/tablacus/following{/other_user}",
"gists_url":"https://api.github.com/users/tablacus/gists{/gist_id}",
"starred_url":"https://api.github.com/users/tablacus/starred{/owner}{/repo}",
"subscriptions_url":"https://api.github.com/users/tablacus/subscriptions",
"organizations_url":"https://api.github.com/users/tablacus/orgs",
"repos_url":"https://api.github.com/users/tablacus/repos",
"events_url":"https://api.github.com/users/tablacus/events{/privacy}",
"received_events_url":"https://api.github.com/users/tablacus/received_events",
"type":"User",
"site_admin":false},"prerelease":false,"created_at":"2020-11-10T14:19:52Z",
"published_at":"2020-11-10T14:23:56Z",
"assets":[{"url":"https://api.github.com/repos/tablacus/TablacusExplorer/releases/assets/28145072",
"id":28145072,
"node_id":"MDEyOlJlbGVhc2VBc3NldDI4MTQ1MDcy",
"name":"te201110.zip",
"label":null,"uploader":{"login":"tablacus",
"id":5156977,
"node_id":"MDQ6VXNlcjUxNTY5Nzc=",
"avatar_url":"https://avatars0.githubusercontent.com/u/5156977?v=4",
"gravatar_id":"",
"url":"https://api.github.com/users/tablacus",
"html_url":"https://github.com/tablacus",
"followers_url":"https://api.github.com/users/tablacus/followers",
"following_url":"https://api.github.com/users/tablacus/following{/other_user}",
"gists_url":"https://api.github.com/users/tablacus/gists{/gist_id}",
"starred_url":"https://api.github.com/users/tablacus/starred{/owner}{/repo}",
"subscriptions_url":"https://api.github.com/users/tablacus/subscriptions",
"organizations_url":"https://api.github.com/users/tablacus/orgs",
"repos_url":"https://api.github.com/users/tablacus/repos",
"events_url":"https://api.github.com/users/tablacus/events{/privacy}",
"received_events_url":"https://api.github.com/users/tablacus/received_events",
"type":"User",
"site_admin":false},"content_type":"application/x-zip-compressed",
"state":"uploaded",
"size":640949,
"created_at":"2020-11-10T14:23:41Z",
"updated_at":"2020-11-10T14:23:44Z",
"browser_download_url":"https://github.com/tablacus/TablacusExplorer/releases/download/20.11.10/te201110.zip"}],"tarball_url":"https://api.github.com/repos/tablacus/TablacusExplorer/tarball/20.11.10",
"zipball_url":"https://api.github.com/repos/tablacus/TablacusExplorer/zipball/20.11.10",
"body":"Adjusted: Blink project\r\n* We are working on the Tablacus Explorer Blink project, which is undergoing a major overhaul. Please use 20.9.3 without updating if you don't have any problems.\r\n* Tablacus Explorer Blink化計画に向けて大規模な改修中です。特に問題のない方はアップデートせずに20.9.3をご使用ください。\r\n* BlinkのJavaScriptではVARIANT TIMEを受け取ると実数(VT_DATE→VT_R8)で受け取ってしまうので、日付を受け渡す場合はUnix epochを渡す仕様に変更しました。\r\n\r\n※20.10.25/30から自動更新する場合は「アドオンの更新」を停止してから行ってください。\r\n\r\nTablacus Explorer Blink project に付いては GitHubのリポジトリ tablacus/TablacusExplorerWebView2 をご覧ください。\r\n\r\n[VirusTotal](https://www.virustotal.com/gui/file/d7984f1b7ece0ec1a4067edb96fdafcb38bfbce706b6a912c430f618d59c9b99/detection)\r\n"}
